kineo_styling/__init__.py
kineo_styling/colors.py
kineo_styling/export.py
kineo_styling/styling.py
kineo_styling/colors/__init__.py
kineo_styling/colors/colors.py
kineo_styling/export/__init__.py
kineo_styling/export/export.py
kineo_styling/styling/__init__.py
kineo_styling/styling/styling.py
kineo_styling-0.0.1.dist-info/LICENSE
kineo_styling-0.0.1.dist-info/METADATA
kineo_styling-0.0.1.dist-info/WHEEL
kineo_styling-0.0.1.dist-info/top_level.txt
kineo_styling-0.0.1.dist-info/RECORD
