Metadata-Version: 2.1
Name: kineo-styling
Version: 0.0.1
Summary: Kineo Styling Library
Author: Jannis Grönberg
Author-email: jannis.groenberg@kineo.ai
Requires-Python: >=3.9
License-File: LICENSE
Requires-Dist: pandas (>=1.3)
Requires-Dist: plotly (>=5.0)
